[
  {
    "id": 1,
    "title": "How Governance and Compliance Saves The World... lolwut?",
    "slug": "how-governance-and-compliance-saves-the-world",
    "author": {
      "id": "ben-link-1",
      "name": "Ben Link",
      "avatar": "/images/users/user-1.png"
    },
    "createdAt": "23 th치ng 11, 2026",
    "roles": ["web-developer", "system-architect"],
    "tags": ["ai", "developers", "leadership", "architecture"],
    "reactions": [
      { "type": "like", "emoji": "游녨", "count": 3 },
      { "type": "love", "emoji": "仇벒잺", "count": 2 },
      { "type": "sad", "emoji": "游땩", "count": 0 },
      { "type": "wow", "emoji": "游땵", "count": 1 },
      { "type": "angry", "emoji": "游땨", "count": 0 }
    ],
    "totalReacts": 6,
    "commentsCount": 0,
    "numberBookmarked": 20
  },

  {
    "id": 2,
    "title": "Why Most Developers Underestimate System Design",
    "slug": "why-most-developers-underestimate-system-design",
    "author": {
      "id": "alex-nguyen-1",
      "name": "Alex Nguyen",
      "avatar": "/images/users/user-1.png"
    },
    "createdAt": "3 th치ng 11, 2026",
    "roles": ["backend-developer", "system-architect"],
    "tags": ["architecture", "backend", "career"],
    "reactions": [
      { "type": "like", "emoji": "游녨", "count": 4 },
      { "type": "love", "emoji": "仇벒잺", "count": 3 },
      { "type": "sad", "emoji": "游땩", "count": 0 },
      { "type": "wow", "emoji": "游땵", "count": 1 },
      { "type": "angry", "emoji": "游땨", "count": 0 }
    ],
    "totalReacts": 8,
    "commentsCount": 4,
    "numberBookmarked": 20
  },

  {
    "id": 3,
    "title": "Getting Started with DevOps for Frontend Developers",
    "slug": "getting-started-with-devops-for-frontend-developers",
    "author": {
      "id": "chris-tran-1",
      "name": "Chris Tran",
      "avatar": "/images/users/user-1.png"
    },
    "createdAt": "3 th치ng 11, 2026",
    "roles": ["frontend-developer", "devops-engineer"],
    "tags": ["devops", "ci-cd", "frontend"],
    "reactions": [
      { "type": "like", "emoji": "游녨", "count": 5 },
      { "type": "love", "emoji": "仇벒잺", "count": 2 },
      { "type": "sad", "emoji": "游땩", "count": 0 },
      { "type": "wow", "emoji": "游땵", "count": 1 },
      { "type": "angry", "emoji": "游땨", "count": 0 }
    ],
    "totalReacts": 8,
    "commentsCount": 2,
    "numberBookmarked": 20
  },

  {
    "id": 4,
    "title": "Clean Architecture Is Not Overkill",
    "slug": "clean-architecture-is-not-overkill",
    "author": {
      "id": "ben-link-1",
      "name": "Ben Link",
      "avatar": "/images/users/user-1.png"
    },
    "createdAt": "25 th치ng 11, 2026",
    "roles": ["system-architect"],
    "tags": ["architecture", "clean-code"],
    "reactions": [
      { "type": "like", "emoji": "游녨", "count": 6 },
      { "type": "love", "emoji": "仇벒잺", "count": 4 },
      { "type": "sad", "emoji": "游땩", "count": 0 },
      { "type": "wow", "emoji": "游땵", "count": 2 },
      { "type": "angry", "emoji": "游땨", "count": 0 }
    ],
    "totalReacts": 12,
    "commentsCount": 3,
    "numberBookmarked": 30
  },

  {
    "id": 5,
    "title": "Monolith vs Microservices: A Practical View",
    "slug": "monolith-vs-microservices-practical-view",
    "author": {
      "id": "alex-nguyen-1",
      "name": "Alex Nguyen",
      "avatar": "/images/users/user-1.png"
    },
    "createdAt": "6 th치ng 11, 2026",
    "roles": ["backend-developer"],
    "tags": ["backend", "microservices"],
    "reactions": [
      { "type": "like", "emoji": "游녨", "count": 7 },
      { "type": "love", "emoji": "仇벒잺", "count": 3 },
      { "type": "sad", "emoji": "游땩", "count": 1 },
      { "type": "wow", "emoji": "游땵", "count": 1 },
      { "type": "angry", "emoji": "游땨", "count": 0 }
    ],
    "totalReacts": 12,
    "commentsCount": 5,
    "numberBookmarked": 18
  },

  {
    "id": 6,
    "title": "Scaling APIs Without Losing Your Mind",
    "slug": "scaling-apis-without-losing-your-mind",
    "author": {
      "id": "alex-nguyen-1",
      "name": "Alex Nguyen",
      "avatar": "/images/users/user-1.png"
    },
    "createdAt": "10 th치ng 11, 2026",
    "roles": ["backend-developer"],
    "tags": ["api", "performance", "backend"],
    "reactions": [
      { "type": "like", "emoji": "游녨", "count": 5 },
      { "type": "love", "emoji": "仇벒잺", "count": 2 },
      { "type": "sad", "emoji": "游땩", "count": 0 },
      { "type": "wow", "emoji": "游땵", "count": 2 },
      { "type": "angry", "emoji": "游땨", "count": 0 }
    ],
    "totalReacts": 9,
    "commentsCount": 1,
    "numberBookmarked": 15
  },

  {
    "id": 7,
    "title": "Why Frontend Developers Should Learn DevOps",
    "slug": "why-frontend-developers-should-learn-devops",
    "author": {
      "id": "chris-tran-1",
      "name": "Chris Tran",
      "avatar": "/images/users/user-1.png"
    },
    "createdAt": "8 th치ng 11, 2026",
    "roles": ["frontend-developer"],
    "tags": ["frontend", "devops"],
    "reactions": [
      { "type": "like", "emoji": "游녨", "count": 8 },
      { "type": "love", "emoji": "仇벒잺", "count": 3 },
      { "type": "sad", "emoji": "游땩", "count": 0 },
      { "type": "wow", "emoji": "游땵", "count": 2 },
      { "type": "angry", "emoji": "游땨", "count": 0 }
    ],
    "totalReacts": 13,
    "commentsCount": 4,
    "numberBookmarked": 22
  },

  {
    "id": 8,
    "title": "CI/CD Pipelines Explained for Beginners",
    "slug": "ci-cd-pipelines-explained-for-beginners",
    "author": {
      "id": "chris-tran-1",
      "name": "Chris Tran",
      "avatar": "/images/users/user-1.png"
    },
    "createdAt": "12 th치ng 11, 2026",
    "roles": ["devops-engineer"],
    "tags": ["ci-cd", "devops"],
    "reactions": [
      { "type": "like", "emoji": "游녨", "count": 6 },
      { "type": "love", "emoji": "仇벒잺", "count": 2 },
      { "type": "sad", "emoji": "游땩", "count": 0 },
      { "type": "wow", "emoji": "游땵", "count": 1 },
      { "type": "angry", "emoji": "游땨", "count": 0 }
    ],
    "totalReacts": 9,
    "commentsCount": 2,
    "numberBookmarked": 17
  }
]
